flics/__init__.py
flics/flics.py
flics/original_code.py
flics/tests/__init__.py
flics/tests/old_results_parser.py
flics/tests/test_results.py
flics-0.1.0.dist-info/METADATA
flics-0.1.0.dist-info/RECORD
flics-0.1.0.dist-info/WHEEL
flics-0.1.0.dist-info/top_level.txt
